{
  "name": "welm-tiny-moe192",
  "description": "WeLM tiny model for pretrain experiments, EP=4, micro_bs=1, seq_len=4096 (from blockv2/tiny_model_for_pretrain_exp.sh)",
  "model": {
    "hidden_dim": 1024,
    "n_heads": 16,
    "n_head_kv": 4,
    "head_dim": 128,
    "nope_dim": 64,
    "n_inner": 3072,
    "moe_n_inner": 512,
    "num_experts": 192,
    "moe_topk": 8,
    "vocab_size": 155648
  },
  "training": {
    "micro_batch_size": 1,
    "seq_length": 4096,
    "tp_size": 1,
    "ep_size": 4
  },
  "shapes": {
    "rms_norm":                         {"M": 4096, "N": 1024},
    "quick_gelu_fwd":                   {"batch_size": 4096, "hidden_dim": 3072},
    "quick_gelu_bwd":                   {"batch_size": 4096, "hidden_dim": 3072},
    "swiglu_bf16":                      {"M": 4096, "N": 3072},
    "swiglu_bf16_bwd":                  {"M": 4096, "N": 3072},
    "swiglu_clamp_bf16":                {"M": 4096, "N": 3072},
    "residual_forward":                 {"M": 4096, "N": 1024},
    "residual_backward":                {"M": 4096, "N": 1024},
    "act_quant":                        {"M": 4096, "N": 1024},
    "act_dequant":                      {"M": 4096, "N": 1024, "block_n": 128},
    "act_transpose_quant":              {"M": 4096, "N": 1024},
    "weight_quant":                     {"M": 1024, "N": 1024},
    "weight_dequant":                   {"M": 1024, "N": 1024, "m_block": 128, "n_block": 128},
    "embedding_backward":              {"NUM_TOKENS": 4096, "VOCAB_SIZE": 155648, "EMBED_DIM": 1024},
    "cuda_add":                         {"M": 4096, "N": 1024},
    "cuda_swiglu_quant":                {"M": 4096, "N": 3072},
    "cuda_act_quant_transpose":         {"M": 4096, "N": 1024},
    "cuda_act_quant_transpose_for_gg":  {"M": 4096, "N": 1024, "NUM_EXPERTS": 48},
    "cuda_cumsum":                      {"ROWS": 4096, "COLS": 8},
    "cuda_topk_to_multihot":            {"N_ROWS": 4096, "K": 8},
    "topk_to_multihot":                 {"N_ROWS": 4096, "K": 8},
    "cuda_topk_expert_bias":            {"ROWS": 4096, "FEA_DIM": 48, "K": 8},
    "cuda_select_topk_grad":            {"ROWS": 4096, "FEA_DIM": 48, "K": 8},
    "cuda_group_limited_topk":          {"ROWS": 4096, "NUM_EXPERTS": 48, "NUM_GROUPS": 1, "TOPK_GROUPS": 1, "TOPK": 8},
    "cuda_permute_v2":                  {"NUM_TOKENS": 4096, "FEATURE_DIM": 1024, "TOPK": 8, "N_EXPERTS": 48},
    "cuda_unpermute_v2":                {"NUM_TOKENS": 4096, "FEATURE_DIM": 1024, "TOPK": 8, "N_EXPERTS": 48},
    "cuda_swiglu_mul_probs_fwd":        {"M": 4096, "N": 512},
    "cuda_swiglu_mul_probs_bwd":        {"M": 4096, "N": 512},
    "cuda_qkv_part_rope":              {"BATCH": 1, "SEQ_LEN": 4096, "Q_HEADS": 16, "KV_HEADS": 4, "HEAD_DIM": 128, "NOPE_DIM": 64},
    "cuda_varlen_qkv_part_rope":       {"TOTAL_SEQ": 4096, "NUM_HEADS": 24, "HEAD_DIM": 128, "HALF_ROPE": 32}
  }
}
